Alert_Behavior/__init__.py
Alert_Behavior/alert.py
Alert_Behavior-1.dist-info/LICENSE.txt
Alert_Behavior-1.dist-info/METADATA
Alert_Behavior-1.dist-info/WHEEL
Alert_Behavior-1.dist-info/top_level.txt
Alert_Behavior-1.dist-info/RECORD
