Metadata-Version: 2.1
Name: Alert-Behavior
Version: 1
Summary: UNKNOWN
Home-page: UNKNOWN
Author: Bishwa Sapkota
Author-email: bishowbs08@gmail.com
License: MIT
Platform: UNKNOWN
Requires-Dist: numpy
Requires-Dist: mediapipe
Requires-Dist: opencv-python
